berryditos
