Metadata-Version: 1.1
Name: berryditos
Version: 0.0.4
Summary: Berryditos is a tool that can edit and burn Raspbian images.
Home-page: https://github.com/tovam/berryditos
Author: tovam
Author-email: tovamdvlp@gmail.com
License: MIT
Keywords: raspberry,raspbian
Platform: UNKNOWN
Classifier: License :: OSI Approved :: MIT License
Classifier: Natural Language :: English
Classifier: Operating System :: OS Independent
Classifier: Programming Language :: Python
Classifier: Programming Language :: Python :: 2
Classifier: Programming Language :: Python :: 3
Classifier: Topic :: Software Development
